{
  "project_info": {
    "project_number": "829986757977",
    "firebase_url": "https://androidproject-e7000.firebaseio.com",
    "project_id": "androidproject-e7000",
    "storage_bucket": "androidproject-e7000.appspot.com"
  },
  "client": [
    {
      "client_info": {
        "mobilesdk_app_id": "1:829986757977:android:49d82763ca6aa8ac",
        "android_client_info": {
          "package_name": "andreiovi.com.traveljournalapp"
        }
      },
      "oauth_client": [
        {
          "client_id": "829986757977-v85nalitonlcugqmk64h9jmlboi4ara1.apps.googleusercontent.com",
          "client_type": 3
        }
      ],
      "api_key": [
        {
          "current_key": "AIzaSyA1q9s1pdePkomoqy_bJrlFiarq2L4NnQg"
        }
      ],
      "services": {
        "analytics_service": {
          "status": 1
        },
        "appinvite_service": {
          "status": 1,
          "other_platform_oauth_client": []
        },
        "ads_service": {
          "status": 2
        }
      }
    }
  ],
  "configuration_version": "1"
}